[
  {
    "chapter": 1,
    "questions": [
      {
        "question": "プレゼントを<A>。",
        "kanji": "贈る",
        "kana": "おくる"
      },
      {
        "question": "誕生日の<A>を買った。",
        "kanji": "贈り物",
        "kana": "おくりもの"
      },
      {
        "question": "デパートの<A>売り場へ行く。",
        "kanji": "贈答品",
        "kana": "ぞうとうひん"
      },
      {
        "question": "図書館に本を<A>した。",
        "kanji": "寄贈",
        "kana": "きぞう"
      },
      {
        "question": "橋を<A>向こう岸へ行く。",
        "kanji": "渡って",
        "kana": "わたって"
      },
      {
        "question": "道路を<A>ときは車に気をつける。",
        "kanji": "渡る",
        "kana": "わたる"
      },
      {
        "question": "花束を<A>。",
        "kanji": "渡す",
        "kana": "わたす"
      },
      {
        "question": "春になると<A>が北へ飛んでいく。",
        "kanji": "渡り鳥",
        "kana": "わたりどり"
      },
      {
        "question": "<A>の手続きをする。",
        "kanji": "渡航",
        "kana": "とこう"
      },
      {
        "question": "お菓子をみんなに<A>。",
        "kanji": "配る",
        "kana": "くばる"
      },
      {
        "question": "子どもの健康に<A>。",
        "kanji": "気を配る",
        "kana": "きをくばる"
      },
      {
        "question": "荷物の<A>が遅れた。",
        "kanji": "配達",
        "kana": "はいたつ"
      },
      {
        "question": "試験の問題用紙を<A>する。",
        "kanji": "配付",
        "kana": "はいふ"
      },
      {
        "question": "将来のことが<A>だ。",
        "kanji": "心配",
        "kana": "しんぱい"
      },
      {
        "question": "<A>で荷物を送る。",
        "kanji": "宅配",
        "kana": "たくはい"
      },
      {
        "question": "手紙が<A>。",
        "kanji": "届く",
        "kana": "とどく"
      },
      {
        "question": "荷物を家まで<A>。",
        "kanji": "届ける",
        "kana": "とどける"
      },
      {
        "question": "幼稚園に子どもを<A>。",
        "kanji": "送り届ける",
        "kana": "おくりとどける"
      },
      {
        "question": "声が遠くまで<A>。",
        "kanji": "届く",
        "kana": "とどく"
      },
      {
        "question": "先生に欠席の<A>を出した。",
        "kanji": "欠席届",
        "kana": "けっせきとどけ"
      },
      {
        "question": "誕生パーティーに友人を<A>。",
        "kanji": "招く",
        "kana": "まねく"
      },
      {
        "question": "遠くから<A>をする。",
        "kanji": "手招き",
        "kana": "てまねき"
      },
      {
        "question": "結婚式に<A>された。",
        "kanji": "招待",
        "kana": "しょうたい"
      },
      {
        "question": "<A>が届いた。",
        "kanji": "招待状",
        "kana": "しょうたいじょう"
      },
      {
        "question": "議会を<A>する。",
        "kanji": "招集",
        "kana": "しょうしゅう"
      },
      {
        "question": "電車に乗るとき<A>を買う。",
        "kanji": "乗車券",
        "kana": "じょうしゃけん"
      },
      {
        "question": "コンサートの<A>を手に入れた。",
        "kanji": "入場券",
        "kana": "にゅうじょうけん"
      },
      {
        "question": "毎日同じ路線を使うので<A>を買った。",
        "kanji": "定期券",
        "kana": "ていきけん"
      },
      {
        "question": "お祝いに一万円分の<A>を贈った。",
        "kanji": "商品券",
        "kana": "しょうひんけん"
      },
      {
        "question": "海外旅行に行くため<A>を申請した。",
        "kanji": "旅券",
        "kana": "りょけん"
      },
      {
        "question": "<A>に就職した。",
        "kanji": "証券会社",
        "kana": "しょうけんがいしゃ"
      }
    ]
  },
  {
    "chapter": 2,
    "questions": [
      {
        "question": "<A>が降っている。",
        "kanji": "雨",
        "kana": "あめ"
      },
      {
        "question": "<A>を食べる",
        "kanji": "ご飯",
        "kana": "ごはん"
      }
    ]
  }
]
